redocs/__init__.py
redocs/admin.py
redocs/api_endpoint.py
redocs/api_parser.py
redocs/apps.py
redocs/models.py
redocs/tests.py
redocs/urls.py
redocs/views.py
redocs/templates/redocs/index.html
django_rest_framework_redocs-0.0.8.dist-info/LICENSE
django_rest_framework_redocs-0.0.8.dist-info/METADATA
django_rest_framework_redocs-0.0.8.dist-info/WHEEL
django_rest_framework_redocs-0.0.8.dist-info/top_level.txt
django_rest_framework_redocs-0.0.8.dist-info/RECORD
