Metadata-Version: 2.1
Name: django-rest-framework-redocs
Version: 0.0.8
Summary: Live API endpoints for django rest framework 1.x & 2.x
Home-page: https://github.com/whitedogg13/django-rest-framework-redocs
Author: Richie Hsieh
Author-email: whitedogg13@gmail.com
License: MIT
Platform: UNKNOWN
Classifier: Development Status :: 5 - Production/Stable
Classifier: Environment :: Web Environment
Classifier: Framework :: Django
Classifier: Intended Audience :: Developers
Classifier: License :: OSI Approved :: MIT License
Classifier: Operating System :: OS Independent
Classifier: Programming Language :: Python
Classifier: Programming Language :: Python :: 2.7
Classifier: Programming Language :: Python :: 3
Classifier: Programming Language :: Python :: 3.4
Classifier: Programming Language :: Python :: 3.5
Classifier: Programming Language :: Python :: 3.6
Requires-Dist: django (>=1.8)
Requires-Dist: djangorestframework (>=3)
